netty_snmp/__init__.py
netty_snmp/_types.py
netty_snmp/utils.py
netty_snmp/device_type/__init__.py
netty_snmp/device_type/device_types.py
netty_snmp/device_type/manufactures/__init__.py
netty_snmp/device_type/manufactures/a10.py
netty_snmp/device_type/manufactures/arista.py
netty_snmp/device_type/manufactures/aruba.py
netty_snmp/device_type/manufactures/cisco.py
netty_snmp/device_type/manufactures/extreme.py
netty_snmp/device_type/manufactures/fortinet.py
netty_snmp/device_type/manufactures/h3c.py
netty_snmp/device_type/manufactures/huawei.py
netty_snmp/device_type/manufactures/juniper.py
netty_snmp/device_type/manufactures/mikrotik.py
netty_snmp/device_type/manufactures/netgear.py
netty_snmp/device_type/manufactures/paloalto.py
netty_snmp/device_type/manufactures/ruckus.py
netty_snmp/device_type/manufactures/ruijie.py
netty_snmp/device_type/manufactures/tp_link.py
netty_snmp/device_type/manufactures/zte.py
netty_snmp/factory/__init__.py
netty_snmp/factory/consts.py
netty_snmp/factory/dispatch.py
netty_snmp/factory/snmp_factory.py
netty_snmp/factory/manufactures/__init__.py
netty_snmp/factory/manufactures/arista.py
netty_snmp/factory/manufactures/aruba.py
netty_snmp/factory/manufactures/cisco.py
netty_snmp/factory/manufactures/fortinet.py
netty_snmp/factory/manufactures/h3c.py
netty_snmp/factory/manufactures/huawei.py
netty_snmp/factory/manufactures/juniper.py
netty_snmp/factory/manufactures/paloalto.py
netty_snmp/factory/manufactures/ruijie.py
netty_snmp-0.1.3.dist-info/METADATA
netty_snmp-0.1.3.dist-info/WHEEL
netty_snmp-0.1.3.dist-info/RECORD
