Metadata-Version: 2.3
Name: netty-snmp
Version: 0.1.3
Summary: Network Device information Discovery via SNMP
Author-email: jeffry <wangxin.jeffry@gmail.com>
Keywords: lldp,netmiko,network-automation,network-device,network-discovery,snmp,textfsm
Classifier: Development Status :: 5 - Production/Stable
Classifier: Intended Audience :: Developers
Classifier: Intended Audience :: System Administrators
Classifier: Intended Audience :: Telecommunications Industry
Classifier: License :: OSI Approved :: BSD License
Classifier: Operating System :: POSIX :: Linux
Classifier: Programming Language :: Python :: 3.11
Classifier: Programming Language :: Python :: 3.12
Classifier: Programming Language :: Python :: 3.13
Classifier: Topic :: Software Development
Classifier: Topic :: Software Development :: Libraries
Classifier: Topic :: Software Development :: Libraries :: Python Modules
Classifier: Topic :: System :: Networking
Classifier: Topic :: System :: Networking :: Monitoring
Classifier: Typing :: Typed
Requires-Python: >=3.11
Requires-Dist: ezsnmp>=1.0.0rc3
Requires-Dist: icmplib>=3.0.4
Requires-Dist: tcppinglib>=2.0.3
